LICENSE
README.md
setup.py
pyPorn/__init__.py
pyPorn/base.py
pyPorn/enums.py
pyPorn/exception.py
pyPorn/py.typed
pyPorn/pyPorn.py
pyPorn/version.py
pyPorn.egg-info/PKG-INFO
pyPorn.egg-info/SOURCES.txt
pyPorn.egg-info/dependency_links.txt
pyPorn.egg-info/not-zip-safe
pyPorn.egg-info/requires.txt
pyPorn.egg-info/top_level.txt
pyPorn/types/__init__.py
pyPorn/types/response.py
pyPorn/types/user.py
pyPorn/types/video.py